omnim/__init__.py
omnim/delegate.py
omnim/expressions.py
omnim/linq.py
omnim/math.py
omnim/nullable.py
omnim/omnim_rng_rust.pyd
omnim/readonly.py
omnim/rng.py
omnim/rx.py
omnim/sb.py
omnim/step.py
omnim/task.py
omnim-0.3.1.dist-info/METADATA
omnim-0.3.1.dist-info/WHEEL
omnim-0.3.1.dist-info/top_level.txt
omnim-0.3.1.dist-info/zip-safe
omnim-0.3.1.dist-info/RECORD
