Metadata-Version: 2.4
Name: omnim
Version: 0.3.1
Home-page: https://github.com/cet-t/omnim
Author: cet
Requires-Dist: numba>=0.57.0
Requires-Dist: numpy>=1.22.0
Dynamic: author
Dynamic: home-page
